setup.py
QM9Importer/__init__.py
QM9Importer/load_data.py
QM9_Dataloader.egg-info/PKG-INFO
QM9_Dataloader.egg-info/SOURCES.txt
QM9_Dataloader.egg-info/dependency_links.txt
QM9_Dataloader.egg-info/top_level.txt